waymo_open_dataset_tf_2_11_0-1.6.1.dist-info/RECORD
waymo_open_dataset_tf_2_11_0-1.6.1.dist-info/WHEEL
waymo_open_dataset_tf_2_11_0-1.6.1.dist-info/METADATA
waymo_open_dataset/label_pb2.py
waymo_open_dataset/dataset_pb2.py
waymo_open_dataset/protos/compressed_lidar_pb2.py
waymo_open_dataset/protos/scenario_pb2.py
waymo_open_dataset/protos/map_pb2.py
waymo_open_dataset/protos/conversion_config_pb2.py
waymo_open_dataset/protos/camera_segmentation_submission_pb2.py
waymo_open_dataset/protos/metrics_pb2.py
waymo_open_dataset/protos/keypoints_metrics_pb2.py
waymo_open_dataset/protos/vector_pb2.py
waymo_open_dataset/protos/sim_agents_metrics_pb2.py
waymo_open_dataset/protos/occupancy_flow_metrics_pb2.py
waymo_open_dataset/protos/breakdown_pb2.py
waymo_open_dataset/protos/segmentation_pb2.py
waymo_open_dataset/protos/occupancy_flow_submission_pb2.py
waymo_open_dataset/protos/motion_metrics_pb2.py
waymo_open_dataset/protos/keypoints_submission_pb2.py
waymo_open_dataset/protos/keypoint_pb2.py
waymo_open_dataset/protos/camera_segmentation_metrics_pb2.py
waymo_open_dataset/protos/submission_pb2.py
waymo_open_dataset/protos/segmentation_metrics_pb2.py
waymo_open_dataset/protos/motion_submission_pb2.py
waymo_open_dataset/protos/segmentation_submission_pb2.py
waymo_open_dataset/protos/box_pb2.py
waymo_open_dataset/protos/camera_segmentation_pb2.py
waymo_open_dataset/protos/sim_agents_submission_pb2.py
waymo_open_dataset/metrics/python/wod_detection_evaluator.py
waymo_open_dataset/metrics/python/motion_metrics.py
waymo_open_dataset/metrics/python/matcher.py
waymo_open_dataset/metrics/python/keypoint_metrics.py
waymo_open_dataset/metrics/python/detection_metrics.py
waymo_open_dataset/metrics/python/config_util_py.py
waymo_open_dataset/metrics/python/tracking_metrics.py
waymo_open_dataset/metrics/ops/py_metrics_ops.py
waymo_open_dataset/metrics/ops/metrics_ops.so
waymo_open_dataset/wdl_limited/camera_segmentation/camera_segmentation_metrics.py
waymo_open_dataset/wdl_limited/camera/libcamera_model.so
waymo_open_dataset/wdl_limited/camera/ops/py_camera_model_ops.py
